{
  "project_info": {
    "project_number": "1013082963478",
    "project_id": "postpc-2021-final-project",
    "storage_bucket": "postpc-2021-final-project.appspot.com"
  },
  "client": [
    {
      "client_info": {
        "mobilesdk_app_id": "1:1013082963478:android:7e35a138d31bce9f333f37",
        "android_client_info": {
          "package_name": "com.example.shareyourfood"
        }
      },
      "oauth_client": [
        {
          "client_id": "1013082963478-h5qktd9sg5pg5s35osjjhjbq8obvfcdj.apps.googleusercontent.com",
          "client_type": 3
        }
      ],
      "api_key": [
        {
          "current_key": "AIzaSyD53kpeoj0gjMxjU098ES2jdpsUggOYulg"
        }
      ],
      "services": {
        "appinvite_service": {
          "other_platform_oauth_client": [
            {
              "client_id": "1013082963478-h5qktd9sg5pg5s35osjjhjbq8obvfcdj.apps.googleusercontent.com",
              "client_type": 3
            }
          ]
        }
      }
    }
  ],
  "configuration_version": "1"
}